summarizer/__init__.py
summarizer/bert_parent.py
summarizer/cluster_features.py
summarizer/coreference_handler.py
summarizer/model_processors copy.py
summarizer/model_processors.py
summarizer/sentence_handler.py
summarizer_yshi0914-0.0.1.dist-info/LICENSE
summarizer_yshi0914-0.0.1.dist-info/METADATA
summarizer_yshi0914-0.0.1.dist-info/WHEEL
summarizer_yshi0914-0.0.1.dist-info/top_level.txt
summarizer_yshi0914-0.0.1.dist-info/RECORD
