Metadata-Version: 2.1
Name: summarizer-yshi0914
Version: 0.0.1
Summary: A BERT-based DBSCAN summarizer package
Home-page: https://github.com/yshi0914/bert-based-extractive-summarizer
Author: James Shi
Author-email: yshi0914@gmail.com
License: UNKNOWN
Platform: UNKNOWN
Classifier: Programming Language :: Python :: 3
Classifier: License :: OSI Approved :: MIT License
Classifier: Operating System :: OS Independent
